{"version":1,"tile":"9/443/205","count":8,"tweets":[{"id":"geoTweetTextOnly-352","text":"このへんワンセグが映らない。","lon":131.49052332,"lat":33.30533893,"img":"twitter.png"},{"id":"geoTweetTextOnly-1080","text":"都町なう。","lon":131.60289,"lat":33.236228,"img":"twitter.png"},{"id":"geoTweetTextOnly-1088","text":"臨時バスがきた。大分まで帰れそう","lon":131.50242382,"lat":33.27975797,"img":"twitter.png"},{"id":"geoTweetTextOnly-1629","text":"研修、そこそこ面白し♪( ´▽｀) ただいま休憩、あと2時間！","lon":131.61300325,"lat":33.23279455,"img":"twitter.png"},{"id":"geoTweetTextOnly-2266","text":"高いところから見てます","lon":131.66637897,"lat":33.42060327,"img":"twitter.png"},{"id":"geoTweetTextOnly-4597","text":"オープンセールでなんか安い！ (ローソン 大分インター店)","lon":131.575743,"lat":33.225368,"img":"twitter.png"},{"id":"geoTweetTextOnly-5175","text":" こんな大変な時に何をやってるんでしょうね、まったく(怒) 上に立つ人間として有り得ないです、早く引き継ぎを済まして去りましょ～ファイティン!!tonight さん(^o^;)","lon":131.59032442,"lat":33.19920544,"img":"twitter.png"},{"id":"geoTweetTextOnly-5353","text":" 情報をRetweetして、みんなで助け合いましょう！","lon":131.6389335,"lat":33.21671777,"img":"twitter.png"}]}