{"version":1,"tile":"9/449/202","count":84,"tweets":[{"id":"geoTweetTextOnly-99","text":"いや仕事やろ？ ログインしてくるの11時やし耐えられんのよね","lon":135.78803123,"lat":34.92387685,"img":"twitter.png"},{"id":"geoTweetTextOnly-112","text":"心配！","lon":135.77664399,"lat":35.01279562,"img":"twitter.png"},{"id":"geoTweetTextOnly-131","text":"余震がまだまだ続きます。落ち着いて行動して下さい。","lon":135.77647554,"lat":34.99513816,"img":"twitter.png"},{"id":"geoTweetTextOnly-290","text":"新幹線止まってるのか。","lon":135.74724513,"lat":34.95320148,"img":"twitter.png"},{"id":"geoTweetTextOnly-453","text":"マグニチュードで、数字みると、関東大震災より大きいんだって","lon":135.7701,"lat":35.00883,"img":"twitter.png"},{"id":"geoTweetTextOnly-454","text":"飛行機もダメだ。仙台空港液化してるらしい。","lon":135.75979012,"lat":34.98684363,"img":"twitter.png"},{"id":"geoTweetTextOnly-477","text":"オラ、東京どこでも歩いて行けるから、こういう時安心 浅草から調布とか歩いてたし","lon":135.7701,"lat":35.00896,"img":"twitter.png"},{"id":"geoTweetTextOnly-523","text":"[ | ^o^ ]僕も川のすぐ近くなんでリアルに来て一番最初にやったことはそういう余裕があるのが心配だ。","lon":135.758227,"lat":34.978394,"img":"twitter.png"},{"id":"geoTweetTextOnly-524","text":"ラーメン奢ってくださいm(_ _)m","lon":135.737,"lat":35.03087,"img":"twitter.png"},{"id":"geoTweetTextOnly-681","text":" 今こそももくろちゃんが、路上ライブで関東を勇気付けるべきだ！！","lon":135.75963468,"lat":35.01753515,"img":"twitter.png"},{"id":"geoTweetTextOnly-706","text":"凄い地震だね！経済的にも凄いダメージだね！","lon":135.78123727,"lat":35.0439378,"img":"twitter.png"},{"id":"geoTweetTextOnly-878","text":"関西も少し揺れた様ですが、とんでもない事になりましたね！このニュースは世界中で緊急速報を流しているようで、夕方に娘から安否を尋ねてきました！お宅のお嬢さんもご心配をされておられるでしょう！","lon":135.78514337,"lat":35.04392188,"img":"twitter.png"},{"id":"geoTweetTextOnly-881","text":"兄は家にいるとメールきました","lon":135.75935927,"lat":35.01720886,"img":"twitter.png"},{"id":"geoTweetTextOnly-1071","text":"第一中学とか適当過ぎる気がする","lon":135.75770848,"lat":35.00330609,"img":"twitter.png"},{"id":"geoTweetTextOnly-1163","text":"イエス！","lon":135.7695,"lat":34.99761,"img":"twitter.png"},{"id":"geoTweetTextOnly-1182","text":"あーー！","lon":135.7682,"lat":34.99849,"img":"twitter.png"},{"id":"geoTweetTextOnly-1190","text":"twitterの何が凄いか分かった気がする。きっとこの連帯感、一体感なんだろな。","lon":135.7598555,"lat":34.98749864,"img":"twitter.png"},{"id":"geoTweetTextOnly-1281","text":"宇宙艦隊止まってるみたい","lon":135.77236488,"lat":35.01709422,"img":"twitter.png"},{"id":"geoTweetTextOnly-1464","text":"京都に到着っ。","lon":135.757752,"lat":34.984369,"img":"twitter.png"},{"id":"geoTweetTextOnly-1466","text":"いぬも、そう思うよ！","lon":135.77236488,"lat":35.01709422,"img":"twitter.png"},{"id":"geoTweetTextOnly-1576","text":"東の方誰も連絡つかないぞー！なんか方法ないのか？","lon":135.78071328,"lat":35.03211828,"img":"twitter.png"},{"id":"geoTweetTextOnly-1679","text":"凄い地震が?","lon":135.78514337,"lat":35.04392188,"img":"twitter.png"},{"id":"geoTweetTextOnly-1697","text":"どう？仙台とか。連絡が取れない","lon":135.76025635,"lat":34.99966883,"img":"twitter.png"},{"id":"geoTweetTextOnly-1731","text":"TIEC のメンバー無事！？","lon":135.8347,"lat":34.99704,"img":"twitter.png"},{"id":"geoTweetTextOnly-1759","text":"この地震は電子書籍化の流れを決定的にしたな。断捨離というコンセプトは地震に強い。電池が持たないスマートフォンは親に持たせられない。やはり万人の安心・安全にはガラケー・らくらくフォンのコンセプトも重要。 #jishin","lon":135.8809,"lat":35.00119,"img":"twitter.png"},{"id":"geoTweetTextOnly-1988","text":"サウナのテレビジョンで、物凄い津波映像やってた","lon":135.7701,"lat":35.00896,"img":"twitter.png"},{"id":"geoTweetTextOnly-2241","text":"訳がわからない…","lon":135.77645848,"lat":35.06344373,"img":"twitter.png"},{"id":"geoTweetTextOnly-2249","text":"おまえの女王さま舐めてたわ。ここまでとはな。。","lon":135.803791,"lat":34.981589,"img":"twitter.png"},{"id":"geoTweetTextOnly-2322","text":"みなさん無事でいてください。。。。","lon":136.10527771,"lat":35.12737387,"img":"twitter.png"},{"id":"geoTweetTextOnly-2364","text":"たこ焼きうめぇ","lon":135.75348056,"lat":34.98991389,"img":"twitter.png"},{"id":"geoTweetTextOnly-2403","text":"二時半過ぎに千里山キャンパスにいて揺れた気がしたが気じゃなっかったらしい","lon":135.74821674,"lat":35.00345718,"img":"twitter.png"},{"id":"geoTweetTextOnly-2689","text":"東北地方で地震。","lon":136.010723,"lat":35.013657,"img":"twitter.png"},{"id":"geoTweetTextOnly-2733","text":"Σ:D「助かります☆ ◎使えるやん、アグネス","lon":136.18590849,"lat":35.14360547,"img":"twitter.png"},{"id":"geoTweetTextOnly-2754","text":"ウェラーズなう。店は無事でした (The Weller's Club)","lon":135.76532811,"lat":35.00627694,"img":"twitter.png"},{"id":"geoTweetTextOnly-2810","text":"危機的状況は理性や建前を吹っ飛ばすなぁ(´Д` )  我に帰った時に自己嫌悪に陥らないような 振る舞いが望まれるが、 まぁ、ねぇ、なんとも・・・","lon":135.759966,"lat":34.973322,"img":"twitter.png"},{"id":"geoTweetTextOnly-2923","text":"地震まだ続いてる、、","lon":135.77650673,"lat":35.06297331,"img":"twitter.png"},{"id":"geoTweetTextOnly-3056","text":"脚をゆっくり休めて休んでください。携帯とiPhoneの充電も万全にね。余震もあります、明日も徒歩移動を強いられるかも。皆無事でありますように。","lon":135.74819578,"lat":35.02639777,"img":"twitter.png"},{"id":"geoTweetTextOnly-3152","text":"かんなぎかかった","lon":135.77941071,"lat":35.02942794,"img":"twitter.png"},{"id":"geoTweetTextOnly-3185","text":"明日の北加賀屋、デイイベントじゃなく、夜になったんだー","lon":135.77941071,"lat":35.02942794,"img":"twitter.png"},{"id":"geoTweetTextOnly-3214","text":"Σ:D「クレーマーは喧嘩OKっす ◎怒りの生命力は強いからね☆ Σ|D「朝までが勝負","lon":136.18590849,"lat":35.14360547,"img":"twitter.png"},{"id":"geoTweetTextOnly-3359","text":"赤ちゃんよく飲みますね。今ンとこ二時間置きです。今晩は僕が番してます。震源が分散して心配。そちらも高層だから心配だよね。大丈夫？“たくさんのんだねぇ！スクスク☆あー赤ちゃん会いたいわー。”","lon":135.74812845,"lat":35.02643213,"img":"twitter.png"},{"id":"geoTweetTextOnly-3376","text":"わかってくれる人がいた！ “ そのままでお願いします”","lon":135.77233523,"lat":35.01710218,"img":"twitter.png"},{"id":"geoTweetTextOnly-3378","text":"アニメトロで、ミルキィホームズかからなかったんじゃないか","lon":135.77239453,"lat":35.01708626,"img":"twitter.png"},{"id":"geoTweetTextOnly-3426","text":"仙台空港の辺り酷い事になってるな","lon":135.75857695,"lat":35.0041984,"img":"twitter.png"},{"id":"geoTweetTextOnly-3495","text":"はい！","lon":135.77884978,"lat":34.99186707,"img":"twitter.png"},{"id":"geoTweetTextOnly-3780","text":"この地震の影響で建て替えが起こるのなら、この際耐震の床面積が大きいビルが立つようにさらに措置を講じる機会か。関東大震災後の後藤新平の東京大改造のように。知事選の直前におこるとは。 #Tokyo","lon":135.9592,"lat":35.01832,"img":"twitter.png"},{"id":"geoTweetTextOnly-3890","text":"モマんち言ったら寝てたわね","lon":135.747156,"lat":34.98468,"img":"twitter.png"},{"id":"geoTweetTextOnly-3995","text":"紅茶いただこう。 (VIE DE FRANCE)","lon":135.703653,"lat":34.979861,"img":"twitter.png"},{"id":"geoTweetTextOnly-4009","text":"滋賀県でもびっくりするほど長く揺れました。東北の方は大丈夫でしょうか。","lon":136.000886,"lat":35.033469,"img":"twitter.png"},{"id":"geoTweetTextOnly-4140","text":"Σ:D「自衛隊は？ ◎あり？","lon":136.1786306,"lat":35.14305375,"img":"twitter.png"},{"id":"geoTweetTextOnly-4147","text":"思わぬ京都泊、そして出張で初和室。和室広い！一応4人部屋なのでお茶菓子独占してテンションアガる。 (ルビノ京都堀川)","lon":135.75331,"lat":35.02305,"img":"twitter.png"},{"id":"geoTweetTextOnly-4171","text":"(∴)^o^)東北・関東地方","lon":135.755201,"lat":34.982883,"img":"twitter.png"},{"id":"geoTweetTextOnly-4198","text":"タイガーマスクのマスク被って東京行くとするか","lon":135.75947932,"lat":35.01706471,"img":"twitter.png"},{"id":"geoTweetTextOnly-4272","text":"(∴)^o^)だから荒れんだ、神の飼い犬などで21人死亡との情報","lon":135.755201,"lat":34.982883,"img":"twitter.png"},{"id":"geoTweetTextOnly-4303","text":"Σ:D「 Don't stop be panic. ◎We think so tweet rate is latest. ΣXD「ゆっくりしていってね！！！","lon":136.18354135,"lat":35.14736479,"img":"twitter.png"},{"id":"geoTweetTextOnly-4354","text":"雪ェ (米原駅)","lon":136.28949881,"lat":35.31458241,"img":"twitter.png"},{"id":"geoTweetTextOnly-4355","text":"ミーティング中で他の人がなんにも言わないので気のせいだと思ってた","lon":135.74925379,"lat":35.00384282,"img":"twitter.png"},{"id":"geoTweetTextOnly-4447","text":"そういえば川俣町は大丈夫かしら？","lon":135.747156,"lat":34.98468,"img":"twitter.png"},{"id":"geoTweetTextOnly-4474","text":"Σ:D「オイオイ中国人、お前達の嫌いな日本鬼子が大量に困ってるぞ ◎金返せ！","lon":136.18516862,"lat":35.14278608,"img":"twitter.png"},{"id":"geoTweetTextOnly-4479","text":"連絡取れてない人は気づいたら、ツイートして下さい！皆が心配してます！","lon":135.76895469,"lat":35.01778039,"img":"twitter.png"},{"id":"geoTweetTextOnly-4526","text":"Σ|D「 さん、元気？","lon":136.18516862,"lat":35.14278608,"img":"twitter.png"},{"id":"geoTweetTextOnly-4570","text":"奇跡的にひかり最終東京行きに乗れた。 (新幹線米原駅)","lon":136.285969,"lat":35.306285,"img":"twitter.png"},{"id":"geoTweetTextOnly-4606","text":"んーどうしよ。w","lon":135.7682,"lat":34.99849,"img":"twitter.png"},{"id":"geoTweetTextOnly-4626","text":"断水らしい。","lon":135.7686,"lat":34.99821,"img":"twitter.png"},{"id":"geoTweetTextOnly-4671","text":"Σ|D「自社の対応より数万なフォロワーの不安を守ろうぜ","lon":136.18590849,"lat":35.14360547,"img":"twitter.png"},{"id":"geoTweetTextOnly-4805","text":"お風呂きた (京極湯)","lon":135.743565,"lat":35.026091,"img":"twitter.png"},{"id":"geoTweetTextOnly-4961","text":"新神戸から訪問先の会社を訪ねても停電だとメイル。下りはうごいてない。新横浜のホテルは満席。あくる日の朝、一番機をとってもらおうとするがなかなかとれないもよう。","lon":136.28157401,"lat":35.3405224,"img":"twitter.png"},{"id":"geoTweetTextOnly-4970","text":"Σ|D「外国人を上手く釣る方法が無いな ◎タイムラインに が居ない件について Σ:D「後方支援","lon":136.1790157,"lat":35.14426816,"img":"twitter.png"},{"id":"geoTweetTextOnly-4982","text":"Σ:D「 センノカゼ 未だに届く 私利私欲","lon":136.1790157,"lat":35.14426816,"img":"twitter.png"},{"id":"geoTweetTextOnly-4990","text":"2006に品川で下車し、社用車で停電だけど泊まれるところに移動。朝早くまた社用車をお借りして、羽田空港一番機で伊丹、タクシーで神戸大学に駆け込む計画。","lon":135.96958142,"lat":35.00758153,"img":"twitter.png"},{"id":"geoTweetTextOnly-5006","text":"段取りばかり考え、こちらの動きをお伝えできていなかったことお詫びです。新横浜で止まったあとは地震のゆれが怖いぐらいだったので、無事であることに感謝。","lon":135.71416646,"lat":34.92322736,"img":"twitter.png"},{"id":"geoTweetTextOnly-5023","text":"三日間は安心できませんかしらね。私は明日DDRでI'm soHappyやろうと思った","lon":135.716565,"lat":34.990982,"img":"twitter.png"},{"id":"geoTweetTextOnly-5081","text":"Σ:D「 さん、夜食を頼むね☆ ◎ さんと協力しながら Σ|D「女子力が頼りです☆","lon":136.18590849,"lat":35.14360547,"img":"twitter.png"},{"id":"geoTweetTextOnly-5238","text":"かえるよー (CLUB METRO)","lon":135.7726928,"lat":35.0170803,"img":"twitter.png"},{"id":"geoTweetTextOnly-5261","text":"北加賀屋、早朝行ったら、迷惑な人かもしれないなぁ","lon":135.77233523,"lat":35.01710218,"img":"twitter.png"},{"id":"geoTweetTextOnly-5437","text":" 遠いわ 現場はのんびりしてますよぉ","lon":136.12619434,"lat":35.04067661,"img":"twitter.png"},{"id":"geoTweetTextOnly-5516","text":"異常なし。 ","lon":135.9458,"lat":34.99623,"img":"twitter.png"},{"id":"geoTweetTextOnly-5579","text":"赤はね","lon":135.816,"lat":34.99257,"img":"twitter.png"},{"id":"geoTweetTextOnly-5594","text":"明日の法事のため、今から島根へ向かいます。","lon":135.92611546,"lat":34.97315289,"img":"twitter.png"},{"id":"geoTweetTextOnly-5616","text":"パルい (橋姫神社)","lon":135.805785,"lat":34.891053,"img":"twitter.png"},{"id":"geoTweetTextOnly-5640","text":"プロジェクトが燃え上がるのは非常にしんどい (´‐д‐｀)","lon":135.7320101,"lat":34.99791317,"img":"twitter.png"},{"id":"geoTweetTextOnly-5700","text":"いやらしい話ですが、 いやらしい話ですよ！ そう言えば、寄付金控除とかいう、 所得控除無かったかな？","lon":135.758634,"lat":34.972704,"img":"twitter.png"},{"id":"geoTweetTextOnly-5721","text":"がんばれ！（謎）","lon":135.85243403,"lat":34.91585624,"img":"twitter.png"},{"id":"geoTweetTextOnly-5733","text":"東海道新幹線。順調に走ってます。東京→新大阪の乗車率は100%を少しうわまわる位でしょうか。デッキに立ってらっしゃるかたがちらほら見えます。ちなみに私が乗ってる新幹線の現在地はマークのところです。","lon":136.037094,"lat":35.070126,"img":"twitter.png"}]}