{"version":1,"tile":"9/458/186","count":4,"tweets":[{"id":"geoTweetTextOnly-1766","text":"【現在地情報付き】 天気：雪  前方の視界が大変悪いです。 走行中の方注意。  地震・津波にも警戒。","lon":142.4397062,"lat":44.00336951,"img":"twitter.png"},{"id":"geoTweetTextOnly-2583","text":"愛別もまぁまぁ揺れたからな。横浜はすごいんだろな。とりあえず生きててよかったな。TwitterとSkypeは使えるみたいだよ。","lon":142.58478921,"lat":43.89961391,"img":"twitter.png"},{"id":"geoTweetTextOnly-3916","text":"携帯が繋がらない","lon":142.3929875,"lat":43.75151018,"img":"twitter.png"},{"id":"geoTweetTextOnly-5484","text":"バスまで90分暇… (旭川ロフト)","lon":142.35913396,"lat":43.76467863,"img":"twitter.png"}]}